ai_research_planner/__init__.py
ai_research_planner/cli.py
ai_research_planner/main.py
ai_research_planner/models.py
ai_research_planner/ai_interface/__init__.py
ai_research_planner/ai_interface/config_manager.py
ai_research_planner/ai_interface/multi_model_client.py
ai_research_planner/execution/__init__.py
ai_research_planner/execution/data_cleaner.py
ai_research_planner/execution/plan_executor.py
ai_research_planner/execution/web_scraper.py
ai_research_planner/memory/__init__.py
ai_research_planner/memory/execution_memory.py
ai_research_planner/planning/__init__.py
ai_research_planner/planning/plan_generator.py
ai_research_planner/planning/plan_templates.py
ai_research_planner/utils/__init__.py
ai_research_planner/utils/config.py
ai_research_planner/utils/logger.py
ai_research_planner-0.0.2.dist-info/METADATA
ai_research_planner-0.0.2.dist-info/WHEEL
ai_research_planner-0.0.2.dist-info/entry_points.txt
ai_research_planner-0.0.2.dist-info/licenses/LICENSE
ai_research_planner-0.0.2.dist-info/RECORD
